{"title":"보안뉴스 ─ Security World","url":"https://www.boannews.com/securityworld/","favicon":"https://www.boannews.com/securityworld/favicon.ico","elements":[{"title":"인도, 국가 차원의 보안산업 재정비에 따라 생체인식...","contents":"인도의 ‘디지털 인디아(Digital India)’ 정책 하에 보안 인프라를 강화하기 위해 노력하고 있다. 인도 정부는 ‘디지털 인디아’ 정책 내에 스마트...","link":"https://www.boannews.com/media/view.asp?idx=105822&mkind=5","retrieved":1649120868269,"image":"https://www.boannews.com/media/upFiles2/2022/03/22033106ss.jpg"},{"title":"[미리보는 SECON & eGISEC 2022] 아...","contents":"물리보안과 사이버보안을 아우르는 국내 최대 통합보안 전시회인 제21회 세계보안엑스포(SECON &amp; eGISEC 2022)는 4월 20일부터 22일까지 3일...","link":"https://www.boannews.com/media/view.asp?idx=105828&mkind=5","retrieved":1649120868270,"image":"https://www.boannews.com/media/upFiles2/2022/03/SECON%20eGISEC%202022(7).jpg"}]}