{"title":"보안뉴스 ─ Security World","url":"https://www.boannews.com/securityworld/","favicon":"https://www.boannews.com/securityworld/favicon.ico","elements":[{"title":"안양시, 지능형교통체계(ITS) 확대 사업 통해 미...","contents":"안양시는 지난 22일 KT컨소시엄과 손잡고 지능형교통체계(ITS) 확대구축 사업에 착수했다고 밝혔다. 안양시는 지난해 44억원을 들여 ITS 1단계 사업으...","link":"https://www.boannews.com/media/view.asp?idx=106437&mkind=5","retrieved":1651202795514,"image":"https://www.boannews.com/media/upFiles2/2022/04/4-142(295).jpg"},{"title":"한서대 항공보안학과, 항공보안공모전에서 16개 중 ...","contents":"한서대학교 항공보안학과가 제1회 미래항공보안포럼과 항공보안 공모전에서 11개상을 수상했다.","link":"https://www.boannews.com/media/view.asp?idx=106426&mkind=5","retrieved":1651134256193,"image":"https://www.boannews.com/media/upFiles2/2022/04/22042802ss.jpg"}]}