{"title":"보안뉴스 ─ Security World","url":"https://www.boannews.com/securityworld/","favicon":"https://www.boannews.com/securityworld/favicon.ico","elements":[{"title":"하이크비전, 프로젝트향 프리미엄 제품에 5년 보증 ...","contents":"영상 분야를 핵심 역량으로 보유한 IoT 솔루션 공급업체 하이크비전(Hikvision)이 프리미엄 프로젝트 제품에 대해 글로벌 보증을 5년으로 연장했다. ...","link":"https://www.boannews.com/media/view.asp?idx=106052&mkind=5","retrieved":1649931580399,"image":"https://www.boannews.com/media/upFiles2/2022/04/22041405ss.jpg"},{"title":"물리보안 통합플랫폼 콘퍼런스 2022, 4월 20일...","contents":"물리보안 통합플랫폼 개발의 현주소를 짚어보고 스마트산단과 스마트마을, 스마트건설현장, 스마트빌딩, 스마트점포 등 각각의 특성에 맞는 통합플랫폼 개발을 함께...","link":"https://www.boannews.com/media/view.asp?idx=105901&mkind=5","retrieved":1649927854766,"image":"https://www.boannews.com/media/upFiles2/2022/04/22040603ss.jpg"}]}